electionguard_verify/__init__.py
electionguard_verify/command_line.py
electionguard_verify/constants.py
electionguard_verify/utils.py
electionguard_verify/verify.py
electionguard_verify-0.1.dist-info/LICENSE
electionguard_verify-0.1.dist-info/METADATA
electionguard_verify-0.1.dist-info/WHEEL
electionguard_verify-0.1.dist-info/entry_points.txt
electionguard_verify-0.1.dist-info/top_level.txt
electionguard_verify-0.1.dist-info/RECORD
