Metadata-Version: 2.1
Name: electionguard-verify
Version: 0.1
Summary: Independent Python verifier for ElectionGuard election results.
Home-page: https://github.com/nickboucher/electionguard-verify
Author: Nicholas Boucher
Author-email: nicholas.d.boucher+electionguardpy@gmail.com
License: MIT
Platform: UNKNOWN
Classifier: Programming Language :: Python :: 3
Classifier: License :: OSI Approved :: MIT License
Classifier: Operating System :: OS Independent
Requires-Python: >=3.8
Requires-Dist: electionguard (>=1.1.15)
